integration_testing_environment/__init__.py
integration_testing_environment/__main__.py
integration_testing_environment/extend/__init__.py
integration_testing_environment/extend/mail_thunder_extend/__init__.py
integration_testing_environment/extend/mail_thunder_extend/mail_thunder_setting.py
integration_testing_environment/integration_testing_environment_ui/__init__.py
integration_testing_environment/integration_testing_environment_ui/editor_main/__init__.py
integration_testing_environment/integration_testing_environment_ui/editor_main/main_ui.py
integration_testing_environment/integration_testing_environment_ui/menu/__init__.py
integration_testing_environment/integration_testing_environment_ui/menu/api_testka_menu/__init__.py
integration_testing_environment/integration_testing_environment_ui/menu/api_testka_menu/build_api_testka_menu.py
integration_testing_environment/integration_testing_environment_ui/menu/auto_control_menu/__init__.py
integration_testing_environment/integration_testing_environment_ui/menu/auto_control_menu/build_autocontrol_menu.py
integration_testing_environment/integration_testing_environment_ui/menu/load_density_menu/__init__.py
integration_testing_environment/integration_testing_environment_ui/menu/load_density_menu/build_load_density_menu.py
integration_testing_environment/integration_testing_environment_ui/menu/web_runner_menu/__init__.py
integration_testing_environment/integration_testing_environment_ui/menu/web_runner_menu/build_webrunner_menu.py
integration_testing_environment/integration_testing_environment_ui/show_code_window/__init__.py
integration_testing_environment/integration_testing_environment_ui/show_code_window/code_window.py
integration_testing_environment/integration_testing_environment_ui/syntax/__init__.py
integration_testing_environment/integration_testing_environment_ui/syntax/syntax_extend.py
integration_testing_environment/integration_testing_environment_ui/syntax/syntax_keyword.py
integration_testing_environment-0.0.21.dist-info/LICENSE
integration_testing_environment-0.0.21.dist-info/METADATA
integration_testing_environment-0.0.21.dist-info/WHEEL
integration_testing_environment-0.0.21.dist-info/top_level.txt
integration_testing_environment-0.0.21.dist-info/RECORD
