Metadata-Version: 2.1
Name: integration-testing-environment
Version: 0.0.21
Summary: Integration testing environment for WEB Testing、GUI Testing、API Testing、Load & Stress Testing
Author-email: JE-Chen <zenmailman@gmail.com>
License: MIT
Project-URL: Homepage, https://github.com/JE-Chen/Integration-testing-environment
Classifier: Programming Language :: Python :: 3.7
Classifier: Development Status :: 2 - Pre-Alpha
Classifier: Environment :: Win32 (MS Windows)
Classifier: Environment :: MacOS X
Classifier: Environment :: X11 Applications
Classifier: License :: OSI Approved :: MIT License
Classifier: Operating System :: OS Independent
Requires-Python: >=3.7
License-File: LICENSE
Requires-Dist: je-editor
Requires-Dist: je-auto-control
Requires-Dist: je-web-runner
Requires-Dist: je-load-density
Requires-Dist: je-api-testka
Provides-Extra: full_extension
Requires-Dist: je-mail-thunder ; extra == 'full_extension'
